btse_futures/__init__.py
btse_futures/auth.py
btse_futures/client.py
btse_futures/config.py
btse_futures/constants.py
btse_futures/index.py
btse_futures/order.py
btse_futures/position.py
btse_futures/status.py
btse_futures/util.py
btse_futures/wallet.py
btse_futures/model/__init__.py
btse_futures/model/orderbook.py
btse_futures/model/trade.py
btse_futures/ws/__init__.py
btse_futures/ws/client.py
btse_futures/ws/connection.py
btse_futures/ws/request.py
btse_python-0.0.2.1.dist-info/LICENSE
btse_python-0.0.2.1.dist-info/METADATA
btse_python-0.0.2.1.dist-info/WHEEL
btse_python-0.0.2.1.dist-info/top_level.txt
btse_python-0.0.2.1.dist-info/RECORD
