Metadata-Version: 2.1
Name: btse-python
Version: 0.0.2.1
Summary: Python module to connect to btse.com
Home-page: https://github.com/yottatix/btse-python
Author: Yottatix
Author-email: st@yottatix.com
License: UNKNOWN
Project-URL: Bug Tracker, https://github.com/yottatix/btse-python/issues
Platform: UNKNOWN
Classifier: Programming Language :: Python :: 3
Classifier: License :: OSI Approved :: MIT License
Classifier: Operating System :: OS Independent
Requires-Python: >=3.6
Requires-Dist: requests
Requires-Dist: websocket-client
